macvendor/__init__.py
macvendor/macvendor.py
macvendor/data/prefix24
macvendor/data/prefix28
macvendor/data/prefix36
macvendor-1.0.12.dist-info/LICENSE.txt
macvendor-1.0.12.dist-info/METADATA
macvendor-1.0.12.dist-info/WHEEL
macvendor-1.0.12.dist-info/entry_points.txt
macvendor-1.0.12.dist-info/top_level.txt
macvendor-1.0.12.dist-info/RECORD
