Metadata-Version: 2.1
Name: macvendor
Version: 1.0.12
Summary: A Python Liberary and CLI Tool for Fiding Vendors of MAC Addresses
Home-page: https://github.com/ThamiMemel/python-macvendor
Author: Thami Memel
Author-email: memelthami@gmail.com
License: UNKNOWN
Project-URL: Bug Reports, https://github.com/ThamiMemel/python-macvendor/issues
Project-URL: Source, https://github.com/ThamiMemel/python-macvendor
Keywords: MAC vendors register OUI
Platform: UNKNOWN
Classifier: Development Status :: 5 - Production/Stable
Classifier: Operating System :: OS Independent 
Classifier: Intended Audience :: Developers
Classifier: Intended Audience :: Information Technology
Classifier: Intended Audience :: System Administrators
Classifier: Intended Audience :: Telecommunications Industry
Classifier: Topic :: Software Development :: Libraries :: Python Modules
Classifier: Topic :: System :: Networking :: Monitoring :: Hardware Watchdog
Classifier: License :: OSI Approved :: MIT License
Classifier: Programming Language :: Python :: 2
Classifier: Programming Language :: Python :: 2.7
Classifier: Programming Language :: Python :: 3
Classifier: Programming Language :: Python :: 3.5
Classifier: Programming Language :: Python :: 3.6
Classifier: Programming Language :: Python :: 3.7
Classifier: Programming Language :: Python :: 3.8
Requires-Python: >=2.7, !=3.0.*, !=3.1.*, !=3.2.*, !=3.3.*, !=3.4.*, <4
Requires-Dist: tabulate
